Full Adder/FA.vhdl
library IEEE;
use IEEE.std_logic_1164.all;

entity FA is
port ( a,b,cin : in std_logic;
	   s,cout : out std_logic);
end FA;

architecture behavioural of FA is
begin
	process (a,b,cin) is
	begin
		s <= a xor b xor cin;
		cout <= (a and b)or(b and cin)or(cin and a);
	end process;
end behavioural;

Full Adder/FA_tb.vhdl
library IEEE;
use IEEE.std_logic_1164.all;
 
entity FA_tb is
end FA_tb; 

architecture tb of FA_tb is
component FA is
port(
  a,b,cin: in std_logic;
  cout,s: out std_logic);
end component;
signal a,b,cin,cout,s :std_logic;
begin

  uut: FA port map(a,b,cin,cout,s);

  process
  begin
    a <= '0';b <= '0';cin <= '0'; wait for 1 ns;
      
    a <= '0';b <= '0';cin <= '1'; wait for 1 ns;
    
    a <= '0';b <= '1';cin <= '0'; wait for 1 ns;
    
    a <= '0';b <= '1';cin <= '1'; wait for 1 ns;
    
    a <= '1';b <= '0';cin <= '0'; wait for 1 ns;
    
    a <= '1';b <= '0';cin <= '1'; wait for 1 ns;
    
    a <= '1';b <= '1';cin <= '0'; wait for 1 ns;
    
    a <= '1';b <= '1';cin <= '1'; wait for 1 ns;
    wait;
  end process;
end tb;

Full Adder/fulladder.vcd
$date
  Tue Dec 26 12:16:40 2023
$end
$version
  GHDL v0
$end
$timescale
  1 fs
$end
$scope module standard $end
$upscope $end
$scope module std_logic_1164 $end
$upscope $end
$scope module fa_tb $end
$var reg 1 ! a $end
$var reg 1 " b $end
$var reg 1 # cin $end
$var reg 1 $ cout $end
$var reg 1 % s $end
$scope module uut $end
$var reg 1 & a $end
$var reg 1 ' b $end
$var reg 1 ( cin $end
$var reg 1 ) s $end
$var reg 1 * cout $end
$upscope $end
$upscope $end
$enddefinitions $end
#0
0!
0"
0#
0$
0%
0&
0'
0(
0)
0*
#1000000
1#
1%
1(
1)
#2000000
1"
0#
1'
0(
#3000000
1#
1$
0%
1(
0)
1*
#4000000
1!
0"
0#
0$
1%
1&
0'
0(
1)
0*
#5000000
1#
1$
0%
1(
0)
1*
#6000000
1"
0#
1'
0(
#7000000
1#
1%
1(
1)
