JK-Flip Flop/JKFF.vhdl
library IEEE;
use IEEE.std_logic_1164.all;
entity JKFF is 
port(clock,reset,j,k : in std_logic;
	Q,Qbar : out std_logic);
end JKFF;

architecture behavioural of JKFF is
signal temp :std_logic:='0';
begin
process(clock,reset)
begin
if (reset = '1') then
	temp<='0';
if (clock='1' and clock'event) then
if (j='0' and k='0') then
	temp<=temp;
elsif (j='0' and k='1') then
	temp<='0';
elsif (j='1' and k='0') then
	temp<='1';
elsif (j='1' and k='1') then
	temp<=not(temp);
else 
	temp<='Z';
end if;end if;end if;
Q<=temp after 10 ns;
Qbar<=not temp after 10 ns;
end process;
end behavioural;

JK-Flip Flop/JKFF_tb.vhdl
library IEEE;
use IEEE.std_logic_1164.all;

entity JKFF_tb is
end JKFF_tb;

architecture tb of JKFF_tb is
component JKFF is
port(clock,reset,j,k : in std_logic;
		Q,Qbar : out std_logic);
end component;
signal clock,reset,j,k : std_logic;
signal Q : std_logic :='0';
signal Qbar : std_logic :='1';
begin
	uut : JKFF port map(clock,reset,j,k,Q,Qbar);
	process
	begin
	reset<='1';wait for 50 ns;
	reset<='0';wait for 50 ns;
	wait;
	end process;

	clk_proc : process
	begin
	clock<='0';wait for 10 ns;
	clock<='1';wait for 10 ns;
	clock<='0';wait for 10 ns;
	clock<='1';wait for 10 ns;
	clock<='0';wait for 10 ns;
	clock<='1';wait for 10 ns;
	clock<='0';wait for 10 ns;
	clock<='1';wait for 10 ns;
	clock<='0';wait for 10 ns;
	clock<='1';wait for 10 ns;
	wait;
	end process;
	
	stim_proc : process
	begin
	j<='0';k<='0';wait for 20 ns;
	j<='0';k<='1';wait for 20 ns;
	j<='1';k<='0';wait for 20 ns;
	j<='1';k<='1';wait for 20 ns;
	j<='0';k<='0';wait for 20 ns;
	wait;
	end process;
end tb;

JK-Flip Flop/JK_FF.vcd
$date
  Tue Dec 26 12:20:19 2023
$end
$version
  GHDL v0
$end
$timescale
  1 fs
$end
$scope module standard $end
$upscope $end
$scope module std_logic_1164 $end
$upscope $end
$scope module jkff_tb $end
$var reg 1 ! clock $end
$var reg 1 " reset $end
$var reg 1 # j $end
$var reg 1 $ k $end
$var reg 1 % q $end
$var reg 1 & qbar $end
$scope module uut $end
$var reg 1 ' clock $end
$var reg 1 ( reset $end
$var reg 1 ) j $end
$var reg 1 * k $end
$var reg 1 + q $end
$var reg 1 , qbar $end
$var reg 1 - temp $end
$upscope $end
$upscope $end
$enddefinitions $end
#0
0!
1"
0#
0$
U%
U&
0'
1(
0)
0*
U+
U,
0-
#10000000
1!
0%
1&
1'
0+
1,
#20000000
0!
1$
0'
1*
0+
1,
#30000000
1!
1'
0+
1,
#40000000
0!
1#
0$
0'
1)
0*
0+
1,
#50000000
1!
0"
1'
0(
0+
1,
#60000000
0!
1$
0'
1*
0+
1,
#70000000
1!
1'
0+
1,
#80000000
0!
0#
0$
0'
0)
0*
0+
1,
#90000000
1!
1'
0+
1,
#100000000
0+
1,
